{
  "required": true,
  "minVersion": "0.8",
  "package": "calebzhou.rdi.craftsphere.mixin",
  "compatibilityLevel": "JAVA_17",
  "mixins": [
    "AccessDisconnectedScreen",
    "AccessSystemDetails",
    "MixinClientPlayNetworkHandler",
    "MixinDisconnectedScreen",
    "MixinNewLoadingOverlay",
    "MixinNoUnicodeFonts",
    "MixinNoUnicodeFonts2",
    "MixinPlayMusic",
    "MixinProtocol",
    "MixinUpdater"
  ],
  "client": [
    "MixinAncientChineseSupport",
    "MixinAncientChn2",
    "MixinClientLoginHandler",
    "MixinConnectScreen",
    "MixinDrawableHelper",
    "MixinFoodDirectEat",
    "MixinPauseMenu",
    "MixinPlayerHud",
    "MixinUsernameChecker",
    "SplashMixin",
    "TitleScreenMixin",
    "WindowTitleMixin"
  ],
  "injectors": {
    "defaultRequire": 1
  }
}
